{
  "dependencies": [
    "@gentleduck/libs"
  ],
  "files": [
    {
      "content": "export * from './scroll-area'\n",
      "path": "scroll-area/index.ts",
      "target": "components/ui/index.ts",
      "type": "registry:ui"
    },
    {
      "content": "import { cn } from '@gentleduck/libs/cn'\nimport { type Direction, useDirection } from '@gentleduck/primitives/direction'\nimport * as React from 'react'\n\ninterface ScrollAreaProps extends React.HTMLAttributes<HTMLDivElement> {\n  viewportClassName?: string\n  viewportRef?: React.Ref<HTMLDivElement>\n}\n\nconst ScrollArea = React.forwardRef<HTMLDivElement, ScrollAreaProps>(\n  ({ children, className, viewportClassName, viewportRef, style, dir, ...props }, ref) => {\n    const direction = useDirection(dir as Direction)\n    return (\n      <div\n        className={cn('relative overflow-hidden', className)}\n        dir={direction}\n        style={style}\n        ref={ref}\n        {...props}\n        data-slot=\"scroll-area\">\n        <div ref={viewportRef} className={cn('scrollbar-none h-full w-full overflow-auto', viewportClassName)}>\n          {children}\n        </div>\n      </div>\n    )\n  },\n)\nScrollArea.displayName = 'ScrollArea'\n\nexport { ScrollArea }\n",
      "path": "scroll-area/scroll-area.tsx",
      "target": "components/ui/scroll-area.tsx",
      "type": "registry:ui"
    }
  ],
  "name": "scroll-area",
  "root_folder": "scroll-area",
  "source": "/registry-ui/src/scroll-area",
  "type": "registry:ui"
}